{"cameraMode":{"drawMode":0,"name":"Shaded","section":"Shading Mode"},"sceneLighting":true,"audioPlay":false,"sceneViewState":{"showFog":true,"showMaterialUpdate":false,"showSkybox":true,"showFlares":true,"showImageEffects":true,"showParticleSystems":true,"showVisualEffectGraphs":true,"m_FxEnabled":true},"in2DMode":false,"pivot":{"x":18.663326263427736,"y":-8.2286376953125,"z":20.42744255065918},"rotation":{"x":-0.10828085988759995,"y":0.11478631943464279,"z":-0.012557173147797585,"w":-0.9874493479728699},"size":23.953039169311525,"orthographic":false}